{
    "file_name": "question_35_variants.json",
    "overall_posix": 22.62885592485396,
    "detailed_scores": [
        {
            "Variation 1": 0.3927512264251709,
            "Variation 2": 139.23120510578156,
            "Variation 3": 17.202412857728845,
            "Variation 4": 139.23120510578156,
            "Variation 5": 139.23120510578156,
            "Variation 6": 17.202412857728845,
            "Variation 7": 17.202412857728845,
            "Variation 8": 17.202412857728845,
            "Variation 9": 139.23120510578156,
            "Variation 10": 17.202412857728845
        }
    ],
    "trace": {
        "prompts": [
            "Are the XXXX (which could imply bones, pulmonary vessels, or other chest structures depending on the context provided in the X-ray) on the chest X-ray abnormal? Please choose from the following two options: [yes, no]\n<image>"
        ],
        "responses": [
            [
                "No, the XXXX on the chest X-ray do not indicate any abnormalities. They are likely to be part of the normal anatomy of the chest, such as bones or pulmonary vessels.",
                "Based on the image provided, it is not possible to definitively determine if the XXXX on the chest X-ray are abnormal. The image is a black and white X-ray, and the XXXX could represent various structures within the chest",
                "Yes",
                "Yes, the XXXX on the chest X-ray are abnormal.",
                "Yes",
                "Yes",
                "Yes, the XXXX on the chest X-ray are abnormal.",
                "Yes, the XXXX on the chest X-ray are abnormal.",
                "Yes, the XXXX on the chest X-ray are abnormal.",
                "Yes",
                "Yes, the XXXX on the chest X-ray are abnormal."
            ]
        ],
        "logprob_matrices": [
            [
                [
                    -448.31979036331177,
                    -467.9573516845703,
                    -30.626175045967102,
                    -155.8787717819214,
                    -30.626175045967102,
                    -30.626175045967102,
                    -155.8787717819214,
                    -155.8787717819214,
                    -155.8787717819214,
                    -30.626175045967102,
                    -155.8787717819214
                ],
                [
                    -432.8357412815094,
                    -496.37996768951416,
                    -28.240172624588013,
                    -150.48042845726013,
                    -28.240172624588013,
                    -28.240172624588013,
                    -150.48042845726013,
                    -150.48042845726013,
                    -150.48042845726013,
                    -28.240172624588013,
                    -150.48042845726013
                ],
                [
                    -432.8357412815094,
                    -496.37996768951416,
                    -28.240172624588013,
                    -150.48042845726013,
                    -28.240172624588013,
                    -28.240172624588013,
                    -150.48042845726013,
                    -150.48042845726013,
                    -150.48042845726013,
                    -28.240172624588013,
                    -150.48042845726013
                ],
                [
                    -432.8357412815094,
                    -496.37996768951416,
                    -28.240172624588013,
                    -150.48042845726013,
                    -28.240172624588013,
                    -28.240172624588013,
                    -150.48042845726013,
                    -150.48042845726013,
                    -150.48042845726013,
                    -28.240172624588013,
                    -150.48042845726013
                ],
                [
                    -407.85953736305237,
                    -455.1050326824188,
                    -29.9169921875,
                    -134.96393513679504,
                    -29.9169921875,
                    -29.9169921875,
                    -134.96393513679504,
                    -134.96393513679504,
                    -134.96393513679504,
                    -29.9169921875,
                    -134.96393513679504
                ],
                [
                    -432.8357412815094,
                    -496.37996768951416,
                    -28.240172624588013,
                    -150.48042845726013,
                    -28.240172624588013,
                    -28.240172624588013,
                    -150.48042845726013,
                    -150.48042845726013,
                    -150.48042845726013,
                    -28.240172624588013,
                    -150.48042845726013
                ],
                [
                    -432.8357412815094,
                    -496.37996768951416,
                    -28.240172624588013,
                    -150.48042845726013,
                    -28.240172624588013,
                    -28.240172624588013,
                    -150.48042845726013,
                    -150.48042845726013,
                    -150.48042845726013,
                    -28.240172624588013,
                    -150.48042845726013
                ],
                [
                    -448.2817623615265,
                    -486.5113492012024,
                    -30.176047563552856,
                    -159.96835851669312,
                    -30.176047563552856,
                    -30.176047563552856,
                    -159.96835851669312,
                    -159.96835851669312,
                    -159.96835851669312,
                    -30.176047563552856,
                    -159.96835851669312
                ],
                [
                    -451.42099261283875,
                    -477.93641209602356,
                    -27.391536474227905,
                    -161.24970269203186,
                    -27.391536474227905,
                    -27.391536474227905,
                    -161.24970269203186,
                    -161.24970269203186,
                    -161.24970269203186,
                    -27.391536474227905,
                    -161.24970269203186
                ],
                [
                    -451.42099261283875,
                    -477.93641209602356,
                    -27.391536474227905,
                    -161.24970269203186,
                    -27.391536474227905,
                    -27.391536474227905,
                    -161.24970269203186,
                    -161.24970269203186,
                    -161.24970269203186,
                    -27.391536474227905,
                    -161.24970269203186
                ],
                [
                    -432.8357412815094,
                    -496.37996768951416,
                    -28.240172624588013,
                    -150.48042845726013,
                    -28.240172624588013,
                    -28.240172624588013,
                    -150.48042845726013,
                    -150.48042845726013,
                    -150.48042845726013,
                    -28.240172624588013,
                    -150.48042845726013
                ]
            ]
        ],
        "prompt_sensitivities": [
            22.62885592485396
        ],
        "posix": 22.62885592485396
    }
}