{
    "file_name": "question_162_variants.json",
    "overall_posix": 0.9494318181818182,
    "detailed_scores": [
        {
            "Variation 1": 0.0,
            "Variation 2": 0.0,
            "Variation 3": 0.0,
            "Variation 4": 5.6875,
            "Variation 5": 0.0,
            "Variation 6": 0.0,
            "Variation 7": 0.0,
            "Variation 8": 0.0,
            "Variation 9": 0.0,
            "Variation 10": 0.0
        }
    ],
    "trace": {
        "prompts": [
            "Are there any noticeable skeletal abnormalities in the chest X-ray? Please choose from the following two options: [yes, no]\n<image>"
        ],
        "responses": [
            [
                "yes",
                "yes",
                "yes",
                "yes",
                "No",
                "yes",
                "yes",
                "yes",
                "yes",
                "yes",
                "yes"
            ]
        ],
        "logprob_matrices": [
            [
                [
                    -6.5625,
                    -6.5625,
                    -6.5625,
                    -6.5625,
                    -12.25,
                    -6.5625,
                    -6.5625,
                    -6.5625,
                    -6.5625,
                    -6.5625,
                    -6.5625
                ],
                [
                    -6.71875,
                    -6.71875,
                    -6.71875,
                    -6.71875,
                    -11.5625,
                    -6.71875,
                    -6.71875,
                    -6.71875,
                    -6.71875,
                    -6.71875,
                    -6.71875
                ],
                [
                    -4.75,
                    -4.75,
                    -4.75,
                    -4.75,
                    -10.8125,
                    -4.75,
                    -4.75,
                    -4.75,
                    -4.75,
                    -4.75,
                    -4.75
                ],
                [
                    -8.3125,
                    -8.3125,
                    -8.3125,
                    -8.3125,
                    -13.6875,
                    -8.3125,
                    -8.3125,
                    -8.3125,
                    -8.3125,
                    -8.3125,
                    -8.3125
                ],
                [
                    -6.53125,
                    -6.53125,
                    -6.53125,
                    -6.53125,
                    -11.5625,
                    -6.53125,
                    -6.53125,
                    -6.53125,
                    -6.53125,
                    -6.53125,
                    -6.53125
                ],
                [
                    -6.71875,
                    -6.71875,
                    -6.71875,
                    -6.71875,
                    -11.9375,
                    -6.71875,
                    -6.71875,
                    -6.71875,
                    -6.71875,
                    -6.71875,
                    -6.71875
                ],
                [
                    -6.09375,
                    -6.09375,
                    -6.09375,
                    -6.09375,
                    -13.625,
                    -6.09375,
                    -6.09375,
                    -6.09375,
                    -6.09375,
                    -6.09375,
                    -6.09375
                ],
                [
                    -6.46875,
                    -6.46875,
                    -6.46875,
                    -6.46875,
                    -11.4375,
                    -6.46875,
                    -6.46875,
                    -6.46875,
                    -6.46875,
                    -6.46875,
                    -6.46875
                ],
                [
                    -6.1875,
                    -6.1875,
                    -6.1875,
                    -6.1875,
                    -11.4375,
                    -6.1875,
                    -6.1875,
                    -6.1875,
                    -6.1875,
                    -6.1875,
                    -6.1875
                ],
                [
                    -5.75,
                    -5.75,
                    -5.75,
                    -5.75,
                    -10.0625,
                    -5.75,
                    -5.75,
                    -5.75,
                    -5.75,
                    -5.75,
                    -5.75
                ],
                [
                    -6.625,
                    -6.625,
                    -6.625,
                    -6.625,
                    -11.5,
                    -6.625,
                    -6.625,
                    -6.625,
                    -6.625,
                    -6.625,
                    -6.625
                ]
            ]
        ],
        "prompt_sensitivities": [
            0.9494318181818182
        ],
        "posix": 0.9494318181818182
    }
}