{
    "file_name": "question_303_variants_results.json",
    "overall_posix": 0.42073863636363634,
    "detailed_scores": [
        {
            "Variation 1": 0.0,
            "Variation 2": 0.125,
            "Variation 3": 0.0,
            "Variation 4": 0.0,
            "Variation 5": 0.0,
            "Variation 6": 0.0,
            "Variation 7": 0.125,
            "Variation 8": 0.0,
            "Variation 9": 0.125,
            "Variation 10": 0.0
        }
    ],
    "trace": {
        "prompts": [
            "Are there any visible lung tumors on the chest X-ray? Please choose from the following two options: [yes, no]\n<image>"
        ],
        "responses": [
            [
                "no",
                "no",
                "yes",
                "no",
                "no",
                "no",
                "no",
                "yes",
                "no",
                "yes",
                "no"
            ]
        ],
        "logprob_matrices": [
            [
                [
                    -6.34375,
                    -6.34375,
                    -6.46875,
                    -6.34375,
                    -6.34375,
                    -6.34375,
                    -6.34375,
                    -6.46875,
                    -6.34375,
                    -6.46875,
                    -6.34375
                ],
                [
                    -9.3125,
                    -9.3125,
                    -7.65625,
                    -9.3125,
                    -9.3125,
                    -9.3125,
                    -9.3125,
                    -7.65625,
                    -9.3125,
                    -7.65625,
                    -9.3125
                ],
                [
                    -8.375,
                    -8.375,
                    -6.84375,
                    -8.375,
                    -8.375,
                    -8.375,
                    -8.375,
                    -6.84375,
                    -8.375,
                    -6.84375,
                    -8.375
                ],
                [
                    -6.34375,
                    -6.34375,
                    -6.46875,
                    -6.34375,
                    -6.34375,
                    -6.34375,
                    -6.34375,
                    -6.46875,
                    -6.34375,
                    -6.46875,
                    -6.34375
                ],
                [
                    -9.4375,
                    -9.4375,
                    -8.875,
                    -9.4375,
                    -9.4375,
                    -9.4375,
                    -9.4375,
                    -8.875,
                    -9.4375,
                    -8.875,
                    -9.4375
                ],
                [
                    -8.3125,
                    -8.3125,
                    -6.625,
                    -8.3125,
                    -8.3125,
                    -8.3125,
                    -8.3125,
                    -6.625,
                    -8.3125,
                    -6.625,
                    -8.3125
                ],
                [
                    -7.625,
                    -7.625,
                    -7.5625,
                    -7.625,
                    -7.625,
                    -7.625,
                    -7.625,
                    -7.5625,
                    -7.625,
                    -7.5625,
                    -7.625
                ],
                [
                    -8.5,
                    -8.5,
                    -7.625,
                    -8.5,
                    -8.5,
                    -8.5,
                    -8.5,
                    -7.625,
                    -8.5,
                    -7.625,
                    -8.5
                ],
                [
                    -7.625,
                    -7.625,
                    -5.6875,
                    -7.625,
                    -7.625,
                    -7.625,
                    -7.625,
                    -5.6875,
                    -7.625,
                    -5.6875,
                    -7.625
                ],
                [
                    -7.25,
                    -7.25,
                    -6.4375,
                    -7.25,
                    -7.25,
                    -7.25,
                    -7.25,
                    -6.4375,
                    -7.25,
                    -6.4375,
                    -7.25
                ],
                [
                    -7.84375,
                    -7.84375,
                    -7.15625,
                    -7.84375,
                    -7.84375,
                    -7.84375,
                    -7.84375,
                    -7.15625,
                    -7.84375,
                    -7.15625,
                    -7.84375
                ]
            ]
        ],
        "prompt_sensitivities": [
            0.42073863636363634
        ],
        "posix": 0.42073863636363634
    }
}