{
    "file_name": "question_138_variants_results.json",
    "overall_posix": 3.0708029486142197,
    "detailed_scores": [
        {
            "Variation 1": 0.0,
            "Variation 2": 1.3125,
            "Variation 3": 1.3125,
            "Variation 4": 0.0,
            "Variation 5": 1.3125,
            "Variation 6": 0.0,
            "Variation 7": 1.2214982765061515,
            "Variation 8": 1.3125,
            "Variation 9": 1.3125,
            "Variation 10": 1.3125
        }
    ],
    "trace": {
        "prompts": [
            "Does the patient have a normal cardiomediastinal silhouette on the chest X-ray? Please choose from the following two options: [yes, no]\n<image>"
        ],
        "responses": [
            [
                "no",
                "no",
                "yes",
                "yes",
                "no",
                "yes",
                "no",
                "Yes, there are visible abnormalities in the cardiomediastinal region seen on the chest X-ray. The X-ray shows a leftward displacement of the heart and an increased distance between the heart and the left lung, which are characteristics of a leftward displacement of the heart.",
                "yes",
                "yes",
                "yes"
            ]
        ],
        "logprob_matrices": [
            [
                [
                    -7.375,
                    -7.375,
                    -6.0625,
                    -6.0625,
                    -7.375,
                    -6.0625,
                    -7.375,
                    -75.77890348434448,
                    -6.0625,
                    -6.0625,
                    -6.0625
                ],
                [
                    -9.75,
                    -9.75,
                    -7.125,
                    -7.125,
                    -9.75,
                    -7.125,
                    -9.75,
                    -81.85262215137482,
                    -7.125,
                    -7.125,
                    -7.125
                ],
                [
                    -9.25,
                    -9.25,
                    -5.71875,
                    -5.71875,
                    -9.25,
                    -5.71875,
                    -9.25,
                    -84.7237548828125,
                    -5.71875,
                    -5.71875,
                    -5.71875
                ],
                [
                    -8.9375,
                    -8.9375,
                    -5.59375,
                    -5.59375,
                    -8.9375,
                    -5.59375,
                    -8.9375,
                    -47.884273171424866,
                    -5.59375,
                    -5.59375,
                    -5.59375
                ],
                [
                    -8.4375,
                    -8.4375,
                    -7.09375,
                    -7.09375,
                    -8.4375,
                    -7.09375,
                    -8.4375,
                    -87.97869873046875,
                    -7.09375,
                    -7.09375,
                    -7.09375
                ],
                [
                    -8.25,
                    -8.25,
                    -6.375,
                    -6.375,
                    -8.25,
                    -6.375,
                    -8.25,
                    -79.53849697113037,
                    -6.375,
                    -6.375,
                    -6.375
                ],
                [
                    -7.09375,
                    -7.09375,
                    -5.34375,
                    -5.34375,
                    -7.09375,
                    -5.34375,
                    -7.09375,
                    -83.73129153251648,
                    -5.34375,
                    -5.34375,
                    -5.34375
                ],
                [
                    -8.8125,
                    -8.8125,
                    -4.9375,
                    -4.9375,
                    -8.8125,
                    -4.9375,
                    -8.8125,
                    -28.490138053894043,
                    -4.9375,
                    -4.9375,
                    -4.9375
                ],
                [
                    -7.90625,
                    -7.90625,
                    -6.03125,
                    -6.03125,
                    -7.90625,
                    -6.03125,
                    -7.90625,
                    -83.3131103515625,
                    -6.03125,
                    -6.03125,
                    -6.03125
                ],
                [
                    -9.5,
                    -9.5,
                    -6.59375,
                    -6.59375,
                    -9.5,
                    -6.59375,
                    -9.5,
                    -88.76453495025635,
                    -6.59375,
                    -6.59375,
                    -6.59375
                ],
                [
                    -8.8125,
                    -8.8125,
                    -6.6875,
                    -6.6875,
                    -8.8125,
                    -6.6875,
                    -8.8125,
                    -81.25941705703735,
                    -6.6875,
                    -6.6875,
                    -6.6875
                ]
            ]
        ],
        "prompt_sensitivities": [
            3.0708029486142197
        ],
        "posix": 3.0708029486142197
    }
}