{
    "file_name": "question_150_variants.json",
    "overall_posix": 0.0,
    "detailed_scores": [
        {
            "Variation 1": 0.0,
            "Variation 2": 0.0,
            "Variation 3": 0.0,
            "Variation 4": 0.0,
            "Variation 5": 0.0,
            "Variation 6": 0.0,
            "Variation 7": 0.0,
            "Variation 8": 0.0,
            "Variation 9": 0.0,
            "Variation 10": 0.0
        }
    ],
    "trace": {
        "prompts": [
            "Does the patient show any evidence of pneumonia on their chest X-ray? Please choose from the following two options: [yes, no]\n<image>"
        ],
        "responses": [
            [
                "The patient's chest x-ray does not show any evidence of pneumonia. ",
                "The patient's chest x-ray does not show any evidence of pneumonia. ",
                "The patient's chest x-ray does not show any evidence of pneumonia. ",
                "The patient's chest x-ray does not show any evidence of pneumonia. ",
                "The patient's chest x-ray does not show any evidence of pneumonia. ",
                "The patient's chest x-ray does not show any evidence of pneumonia. ",
                "The patient's chest x-ray does not show any evidence of pneumonia. ",
                "The patient's chest x-ray does not show any evidence of pneumonia. ",
                "The patient's chest x-ray does not show any evidence of pneumonia. ",
                "The patient's chest x-ray does not show any evidence of pneumonia. ",
                "The patient's chest x-ray does not show any evidence of pneumonia. "
            ]
        ],
        "logprob_matrices": [
            [
                [
                    -41.1686608136888,
                    -41.1686608136888,
                    -41.1686608136888,
                    -41.1686608136888,
                    -41.1686608136888,
                    -41.1686608136888,
                    -41.1686608136888,
                    -41.1686608136888,
                    -41.1686608136888,
                    -41.1686608136888,
                    -41.1686608136888
                ],
                [
                    -40.37512213501077,
                    -40.37512213501077,
                    -40.37512213501077,
                    -40.37512213501077,
                    -40.37512213501077,
                    -40.37512213501077,
                    -40.37512213501077,
                    -40.37512213501077,
                    -40.37512213501077,
                    -40.37512213501077,
                    -40.37512213501077
                ],
                [
                    -41.87639215850686,
                    -41.87639215850686,
                    -41.87639215850686,
                    -41.87639215850686,
                    -41.87639215850686,
                    -41.87639215850686,
                    -41.87639215850686,
                    -41.87639215850686,
                    -41.87639215850686,
                    -41.87639215850686,
                    -41.87639215850686
                ],
                [
                    -41.64076129777504,
                    -41.64076129777504,
                    -41.64076129777504,
                    -41.64076129777504,
                    -41.64076129777504,
                    -41.64076129777504,
                    -41.64076129777504,
                    -41.64076129777504,
                    -41.64076129777504,
                    -41.64076129777504,
                    -41.64076129777504
                ],
                [
                    -40.54865526644426,
                    -40.54865526644426,
                    -40.54865526644426,
                    -40.54865526644426,
                    -40.54865526644426,
                    -40.54865526644426,
                    -40.54865526644426,
                    -40.54865526644426,
                    -40.54865526644426,
                    -40.54865526644426,
                    -40.54865526644426
                ],
                [
                    -41.24888425391555,
                    -41.24888425391555,
                    -41.24888425391555,
                    -41.24888425391555,
                    -41.24888425391555,
                    -41.24888425391555,
                    -41.24888425391555,
                    -41.24888425391555,
                    -41.24888425391555,
                    -41.24888425391555,
                    -41.24888425391555
                ],
                [
                    -40.96755261885528,
                    -40.96755261885528,
                    -40.96755261885528,
                    -40.96755261885528,
                    -40.96755261885528,
                    -40.96755261885528,
                    -40.96755261885528,
                    -40.96755261885528,
                    -40.96755261885528,
                    -40.96755261885528,
                    -40.96755261885528
                ],
                [
                    -41.07678125410348,
                    -41.07678125410348,
                    -41.07678125410348,
                    -41.07678125410348,
                    -41.07678125410348,
                    -41.07678125410348,
                    -41.07678125410348,
                    -41.07678125410348,
                    -41.07678125410348,
                    -41.07678125410348,
                    -41.07678125410348
                ],
                [
                    -40.80020075858465,
                    -40.80020075858465,
                    -40.80020075858465,
                    -40.80020075858465,
                    -40.80020075858465,
                    -40.80020075858465,
                    -40.80020075858465,
                    -40.80020075858465,
                    -40.80020075858465,
                    -40.80020075858465,
                    -40.80020075858465
                ],
                [
                    -41.464286000595166,
                    -41.464286000595166,
                    -41.464286000595166,
                    -41.464286000595166,
                    -41.464286000595166,
                    -41.464286000595166,
                    -41.464286000595166,
                    -41.464286000595166,
                    -41.464286000595166,
                    -41.464286000595166,
                    -41.464286000595166
                ],
                [
                    -41.881225348439784,
                    -41.881225348439784,
                    -41.881225348439784,
                    -41.881225348439784,
                    -41.881225348439784,
                    -41.881225348439784,
                    -41.881225348439784,
                    -41.881225348439784,
                    -41.881225348439784,
                    -41.881225348439784,
                    -41.881225348439784
                ]
            ]
        ],
        "prompt_sensitivities": [
            0.0
        ],
        "posix": 0.0
    }
}