{
    "file_name": "question_68_variants.json",
    "overall_posix": 0.005619272210429937,
    "detailed_scores": [
        {
            "Variation 1": 0.0,
            "Variation 2": 0.015768884800148524,
            "Variation 3": 0.0,
            "Variation 4": 0.0,
            "Variation 5": 0.0,
            "Variation 6": 0.0,
            "Variation 7": 0.0,
            "Variation 8": 0.0,
            "Variation 9": 0.0,
            "Variation 10": 0.0
        }
    ],
    "trace": {
        "prompts": [
            "Is the heart size enlarged on the chest X-ray? Please choose from the following two options: [yes, no]\n<image>"
        ],
        "responses": [
            [
                "The chest x-ray shows a normal heart size. ",
                "The chest x-ray shows a normal heart size. ",
                "The chest x-ray does not show an enlarged heart. ",
                "The chest x-ray shows a normal heart size. ",
                "The chest x-ray shows a normal heart size. ",
                "The chest x-ray shows a normal heart size. ",
                "The chest x-ray shows a normal heart size. ",
                "The chest x-ray shows a normal heart size. ",
                "The chest x-ray shows a normal heart size. ",
                "The chest x-ray shows a normal heart size. ",
                "The chest x-ray shows a normal heart size. "
            ]
        ],
        "logprob_matrices": [
            [
                [
                    -42.189765627925226,
                    -42.189765627925226,
                    -41.9216945863227,
                    -42.189765627925226,
                    -42.189765627925226,
                    -42.189765627925226,
                    -42.189765627925226,
                    -42.189765627925226,
                    -42.189765627925226,
                    -42.189765627925226,
                    -42.189765627925226
                ],
                [
                    -42.53168017558346,
                    -42.53168017558346,
                    -42.038295633508824,
                    -42.53168017558346,
                    -42.53168017558346,
                    -42.53168017558346,
                    -42.53168017558346,
                    -42.53168017558346,
                    -42.53168017558346,
                    -42.53168017558346,
                    -42.53168017558346
                ],
                [
                    -42.49030994313216,
                    -42.49030994313216,
                    -41.98556788274436,
                    -42.49030994313216,
                    -42.49030994313216,
                    -42.49030994313216,
                    -42.49030994313216,
                    -42.49030994313216,
                    -42.49030994313216,
                    -42.49030994313216,
                    -42.49030994313216
                ],
                [
                    -42.69476176813623,
                    -42.69476176813623,
                    -42.36381549138605,
                    -42.69476176813623,
                    -42.69476176813623,
                    -42.69476176813623,
                    -42.69476176813623,
                    -42.69476176813623,
                    -42.69476176813623,
                    -42.69476176813623,
                    -42.69476176813623
                ],
                [
                    -42.26966578204883,
                    -42.26966578204883,
                    -41.736988175995066,
                    -42.26966578204883,
                    -42.26966578204883,
                    -42.26966578204883,
                    -42.26966578204883,
                    -42.26966578204883,
                    -42.26966578204883,
                    -42.26966578204883,
                    -42.26966578204883
                ],
                [
                    -42.15625886408452,
                    -42.15625886408452,
                    -41.6205590275531,
                    -42.15625886408452,
                    -42.15625886408452,
                    -42.15625886408452,
                    -42.15625886408452,
                    -42.15625886408452,
                    -42.15625886408452,
                    -42.15625886408452,
                    -42.15625886408452
                ],
                [
                    -43.19965991274512,
                    -43.19965991274512,
                    -42.66348319552344,
                    -43.19965991274512,
                    -43.19965991274512,
                    -43.19965991274512,
                    -43.19965991274512,
                    -43.19965991274512,
                    -43.19965991274512,
                    -43.19965991274512,
                    -43.19965991274512
                ],
                [
                    -42.46211863085773,
                    -42.46211863085773,
                    -42.04128594028589,
                    -42.46211863085773,
                    -42.46211863085773,
                    -42.46211863085773,
                    -42.46211863085773,
                    -42.46211863085773,
                    -42.46211863085773,
                    -42.46211863085773,
                    -42.46211863085773
                ],
                [
                    -42.80744941730518,
                    -42.80744941730518,
                    -42.444415190591826,
                    -42.80744941730518,
                    -42.80744941730518,
                    -42.80744941730518,
                    -42.80744941730518,
                    -42.80744941730518,
                    -42.80744941730518,
                    -42.80744941730518,
                    -42.80744941730518
                ],
                [
                    -42.75959711880569,
                    -42.75959711880569,
                    -42.286106047009525,
                    -42.75959711880569,
                    -42.75959711880569,
                    -42.75959711880569,
                    -42.75959711880569,
                    -42.75959711880569,
                    -42.75959711880569,
                    -42.75959711880569,
                    -42.75959711880569
                ],
                [
                    -42.4572170183892,
                    -42.4572170183892,
                    -42.03250272748119,
                    -42.4572170183892,
                    -42.4572170183892,
                    -42.4572170183892,
                    -42.4572170183892,
                    -42.4572170183892,
                    -42.4572170183892,
                    -42.4572170183892,
                    -42.4572170183892
                ]
            ]
        ],
        "prompt_sensitivities": [
            0.005619272210429937
        ],
        "posix": 0.005619272210429937
    }
}