{
    "file_name": "question_308_variants.json",
    "overall_posix": 0.03614221632354908,
    "detailed_scores": [
        {
            "Variation 1": 0.005586592178770999,
            "Variation 2": 0.016759776536312887,
            "Variation 3": 0.011049723756906049,
            "Variation 4": 0.011173184357541888,
            "Variation 5": 0.011111111111111072,
            "Variation 6": 0.022346368715083775,
            "Variation 7": 0.011173184357541888,
            "Variation 8": 0.005555555555555536,
            "Variation 9": 0.01666666666666672,
            "Variation 10": 0.25
        }
    ],
    "trace": {
        "prompts": [
            "Is there evidence of enlarged lymph nodes on the chest X-ray? Please choose from the following two options: [yes, no]\n<image>"
        ],
        "responses": [
            [
                "<s> Is there evidence of enlarged lymph nodes on the chest X-ray? Please choose from the following two options: [yes, no]\n<image> 1.\n 2.\n 3.\n 4.\n 5.\n 6.\n 7.\n 8.\n 9.\n 10.\n 11.\n 12.",
                "<s> Is there wvidence of enlarged lymph nodes on the chest X-ray? Please choose from the following two options: [yes, no]\n<image> 1.\n 2.\n 3.\n 4.\n 5.\n 6.\n 7.\n 8.\n 9.\n 10.\n 11.\n 12.",
                "<s> Is there evidenec of enlarged lymph nodes on the chest X-ray? Please choose from rhe following two options: [yes, no]\n<image> 1.\n 2.\n 3.\n 4.\n 5.\n 6.\n 7.\n 8.\n 9.\n 10.\n 11.\n 12.",
                "<s> Is there evidence of enlarged lymph nodes on the chest X-rayg? Palease choose from the following two options: [yes, no]\n<image> 1.\n 2.\n 3.\n 4.\n 5.\n 6.\n 7.\n 8.\n 9.\n 10.\n 11.\n 12.",
                "<s> Is there evdence of enlarged lymph nodes on the chest X-ray? Pleaise choose from the following two options: [yes, no]\n<image> 1.\n 2.\n 3.\n 4.\n 5.\n 6.\n 7.\n 8.\n 9.\n 10.\n 11.\n 12.",
                "<s> Is there evidence of enlargled lymph nodes on the chest X-ray? Olease choose from the following two options: [yes, no]\n<image> 1.\n 2.\n 3.\n 4.\n 5.\n 6.\n 7.\n 8.\n 9.\n 10.\n 11.\n 12.",
                "<s> Is there evidnece of enlarged lymph nodes on the chest X-ray? Please choose from the follwoing two options: [yes, no]\n<image> 1.\n 2.\n 3.\n 4.\n 5.\n 6.\n 7.\n 8.\n 9.\n 10.\n 11.\n 12.",
                "<s> Is there evidence of enlarged lymph nodew on the chest X-ray? Plrase choose from the following two options: [yes, no]\n<image> 1.\n 2.\n 3.\n 4.\n 5.\n 6.\n 7.\n 8.\n 9.\n 10.\n 11.\n 12.",
                "<s> Is there evidencwe of enlarged lymph nodes on the chest X-ray? Please choose from the following two options: [yes, no]\n<image> 1.\n 2.\n 3.\n 4.\n 5.\n 6.\n 7.\n 8.\n 9.\n 10.\n 11.\n 12.",
                "<s> Is there evidence of enlargwed lymph nodes on the chest X-ray? Please choose from the following two option:s [yes, no]\n<image> 1.\n 2.\n 3.\n 4.\n 5.\n 6.\n 7.\n 8.\n 9.\n 10.\n 11.\n 12.",
                "<s> Is there evidence of enlbarged lymph nodes on the chest X-ray? Please choose from the following two options: [yws, no]\n<image> [y/n]\n [y, n]\n [y, n]\n [y, n]\n [y, n]\n [y, n]\n [y, n]\n [y, n]\n [y"
            ]
        ],
        "sensitivities": [
            0.03614221632354908
        ],
        "posix": 0.03614221632354908
    }
}